leicaautomator/__init__.py
leicaautomator/automator.py
leicaautomator/utils.py
leicaautomator/viewer.py
leicaautomator-0.0.2.dist-info/DESCRIPTION.rst
leicaautomator-0.0.2.dist-info/METADATA
leicaautomator-0.0.2.dist-info/metadata.json
leicaautomator-0.0.2.dist-info/RECORD
leicaautomator-0.0.2.dist-info/top_level.txt
leicaautomator-0.0.2.dist-info/WHEEL
