Metadata-Version: 2.0
Name: leicaautomator
Version: 0.0.2
Summary: Automate scans on Leica SPX microscopes
Home-page: https://github.com/arve0/leicaautomator
Author: Arve Seljebu
Author-email: arve.seljebu@gmail.com
License: MIT
Keywords: leicaautomator
Platform: UNKNOWN
Classifier: Development Status :: 2 - Pre-Alpha
Classifier: Intended Audience :: Developers
Classifier: License :: OSI Approved :: MIT License
Classifier: Natural Language :: English
Classifier: Programming Language :: Python :: 2
Classifier: Programming Language :: Python :: 2.7
Classifier: Programming Language :: Python :: 3
Classifier: Programming Language :: Python :: 3.4
Requires-Dist: scipy
Requires-Dist: scikit-image
Requires-Dist: numpy
Requires-Dist: matplotlib
Requires-Dist: leicascanningtemplate
Requires-Dist: leicacam
Requires-Dist: leicaexperiment
